{
	"name": "pipeline Load Summary data to Synapse Summary Table",
	"properties": {
		"activities": [
			{
				"name": "Data flow1",
				"type": "ExecuteDataFlow",
				"dependsOn": [],
				"policy": {
					"timeout": "0.12:00:00",
					"retry": 0,
					"retryIntervalInSeconds": 30,
					"secureOutput": false,
					"secureInput": false
				},
				"userProperties": [],
				"typeProperties": {
					"dataflow": {
						"referenceName": "move_summarydata_to_synapse",
						"type": "DataFlowReference",
						"parameters": {
							"dataflow_param_fiscalyear": {
								"value": "@pipeline().parameters.pipeline_param_fiscalyear",
								"type": "Expression"
							}
						}
					},
					"staging": {
						"linkedService": {
							"referenceName": "link_to_synapse_datalake",
							"type": "LinkedServiceReference"
						},
						"folderPath": "nycpayroll-synapse-akinola-olowookere/dirStaging"
					},
					"compute": {
						"coreCount": 8,
						"computeType": "General"
					},
					"traceLevel": "Fine"
				}
			}
		],
		"parameters": {
			"pipeline_param_fiscalyear": {
				"type": "int",
				"defaultValue": 2020
			}
		},
		"annotations": [],
		"lastPublishTime": "2022-12-29T17:07:07Z"
	},
	"type": "Microsoft.DataFactory/factories/pipelines"
}